uquake/grid/__init__.py
uquake/grid/base.py
uquake/grid/client.py
uquake/grid/nlloc.py
uquake.grid-0.1.0.dist-info/LICENSE
uquake.grid-0.1.0.dist-info/WHEEL
uquake.grid-0.1.0.dist-info/METADATA
uquake.grid-0.1.0.dist-info/RECORD
