Metadata-Version: 2.1
Name: uquake.grid
Version: 0.1.0
Summary: grid utility for uQuake
License: MIT
Author: jpmercier
Author-email: jpmercier01@gmail.com
Requires-Python: >=3.8,<4.0
Classifier: License :: OSI Approved :: MIT License
Classifier: Programming Language :: Python :: 3
Classifier: Programming Language :: Python :: 3.8
Classifier: Programming Language :: Python :: 3.9
